{"orig":"/Users/kalaverin/src/lang/nim/lib/posix/linux.nim","nimble":"stdlib","moduleDescription":"Flags of <tt class=\"docutils literal\"><span class=\"pre\"><span class=\"Identifier\">clone</span></span></tt> syscall. See <a class=\"reference external\" href=\"https://man7.org/linux/man-pages/man2/clone.2.html\">clone syscall manual</a> for more information.","entries":[{"name":"CSIGNAL","type":"skConst","line":7,"col":2,"code":"CSIGNAL = 0x000000FF'i32"},{"name":"CLONE_VM","type":"skConst","line":8,"col":2,"code":"CLONE_VM = 0x00000100'i32"},{"name":"CLONE_FS","type":"skConst","line":9,"col":2,"code":"CLONE_FS = 0x00000200'i32"},{"name":"CLONE_FILES","type":"skConst","line":10,"col":2,"code":"CLONE_FILES = 0x00000400'i32"},{"name":"CLONE_SIGHAND","type":"skConst","line":11,"col":2,"code":"CLONE_SIGHAND = 0x00000800'i32"},{"name":"CLONE_PIDFD","type":"skConst","line":12,"col":2,"code":"CLONE_PIDFD = 0x00001000'i32"},{"name":"CLONE_PTRACE","type":"skConst","line":13,"col":2,"code":"CLONE_PTRACE = 0x00002000'i32"},{"name":"CLONE_VFORK","type":"skConst","line":14,"col":2,"code":"CLONE_VFORK = 0x00004000'i32"},{"name":"CLONE_PARENT","type":"skConst","line":15,"col":2,"code":"CLONE_PARENT = 0x00008000'i32"},{"name":"CLONE_THREAD","type":"skConst","line":16,"col":2,"code":"CLONE_THREAD = 0x00010000'i32"},{"name":"CLONE_NEWNS","type":"skConst","line":17,"col":2,"code":"CLONE_NEWNS = 0x00020000'i32"},{"name":"CLONE_SYSVSEM","type":"skConst","line":18,"col":2,"code":"CLONE_SYSVSEM = 0x00040000'i32"},{"name":"CLONE_SETTLS","type":"skConst","line":19,"col":2,"code":"CLONE_SETTLS = 0x00080000'i32"},{"name":"CLONE_PARENT_SETTID","type":"skConst","line":20,"col":2,"code":"CLONE_PARENT_SETTID = 0x00100000'i32"},{"name":"CLONE_CHILD_CLEARTID","type":"skConst","line":21,"col":2,"code":"CLONE_CHILD_CLEARTID = 0x00200000'i32"},{"name":"CLONE_DETACHED","type":"skConst","line":22,"col":2,"code":"CLONE_DETACHED = 0x00400000'i32"},{"name":"CLONE_UNTRACED","type":"skConst","line":23,"col":2,"code":"CLONE_UNTRACED = 0x00800000'i32"},{"name":"CLONE_CHILD_SETTID","type":"skConst","line":24,"col":2,"code":"CLONE_CHILD_SETTID = 0x01000000'i32"},{"name":"CLONE_NEWCGROUP","type":"skConst","line":25,"col":2,"code":"CLONE_NEWCGROUP = 0x02000000'i32"},{"name":"CLONE_NEWUTS","type":"skConst","line":26,"col":2,"code":"CLONE_NEWUTS = 0x04000000'i32"},{"name":"CLONE_NEWIPC","type":"skConst","line":27,"col":2,"code":"CLONE_NEWIPC = 0x08000000'i32"},{"name":"CLONE_NEWUSER","type":"skConst","line":28,"col":2,"code":"CLONE_NEWUSER = 0x10000000'i32"},{"name":"CLONE_NEWPID","type":"skConst","line":29,"col":2,"code":"CLONE_NEWPID = 0x20000000'i32"},{"name":"CLONE_NEWNET","type":"skConst","line":30,"col":2,"code":"CLONE_NEWNET = 0x40000000'i32"},{"name":"CLONE_IO","type":"skConst","line":31,"col":2,"code":"CLONE_IO = 0x80000000'i32"},{"name":"clone","type":"skProc","line":35,"col":0,"code":"proc clone(fn: pointer; child_stack: pointer; flags: cint; arg: pointer;\n           ptid: ptr Pid; tls: pointer; ctid: ptr Pid): cint {.importc,\n    header: \"<sched.h>\", raises: [], tags: [], forbids: [].}","signature":{"return":"cint","arguments":[{"name":"fn","type":"pointer"},{"name":"child_stack","type":"pointer"},{"name":"flags","type":"cint"},{"name":"arg","type":"pointer"},{"name":"ptid","type":"ptr Pid"},{"name":"tls","type":"pointer"},{"name":"ctid","type":"ptr Pid"}],"pragmas":["importc","header: \"<sched.h>\"","raises: []","tags: []","forbids: []"]}},{"name":"pipe2","type":"skProc","line":39,"col":0,"code":"proc pipe2(a: array[0 .. 1, cint]; flags: cint): cint {.importc,\n    header: \"<unistd.h>\", raises: [], tags: [], forbids: [].}","signature":{"return":"cint","arguments":[{"name":"a","type":"array[0 .. 1, cint]"},{"name":"flags","type":"cint"}],"pragmas":["importc","header: \"<unistd.h>\"","raises: []","tags: []","forbids: []"]}}]}