{"orig":"/Users/kalaverin/src/lang/nim/lib/pure/ropes.nim","nimble":"stdlib","moduleDescription":"This module contains support for a <span id=\"rope_1\">rope</span> data type. Ropes can represent very long strings efficiently; in particular, concatenation is done in O(1) instead of O(n). They are essentially concatenation trees that are only flattened when converting to a native Nim string. The empty string is represented by <tt class=\"docutils literal\"><span class=\"pre\"><span class=\"Keyword\">nil</span></span></tt>. Ropes are immutable and subtrees can be shared without copying. Leaves can be cached for better memory efficiency at the cost of runtime efficiency.","entries":[{"name":"Rope","type":"skType","line":35,"col":20,"code":"Rope {.acyclic.} = ref object","description":"A rope data type. The empty rope is represented by <tt class=\"docutils literal\"><span class=\"pre\"><span class=\"Keyword\">nil</span></span></tt>."},{"name":"len","type":"skProc","line":49,"col":0,"code":"proc len(a: Rope): int {.gcsafe, extern: \"nro$1\", raises: [], tags: [],\n                         forbids: [].}","signature":{"return":"int","arguments":[{"name":"a","type":"Rope"}],"pragmas":["gcsafe","extern: \"nro$1\"","raises: []","tags: []","forbids: []"]},"description":"The rope's length."},{"name":"rope","type":"skProc","line":130,"col":0,"code":"proc rope(s: string = \"\"): Rope {.gcsafe, extern: \"nro$1Str\", raises: [],\n                                  tags: [], forbids: [].}","signature":{"return":"Rope","arguments":[{"name":"s","type":"string","default":"\"\""}],"pragmas":["gcsafe","extern: \"nro$1Str\"","raises: []","tags: []","forbids: []"]},"description":"Converts a string to a rope."},{"name":"rope","type":"skProc","line":149,"col":0,"code":"proc rope(i: BiggestInt): Rope {.gcsafe, extern: \"nro$1BiggestInt\", raises: [],\n                                 tags: [], forbids: [].}","signature":{"return":"Rope","arguments":[{"name":"i","type":"BiggestInt"}],"pragmas":["gcsafe","extern: \"nro$1BiggestInt\"","raises: []","tags: []","forbids: []"]},"description":"Converts an int to a rope."},{"name":"rope","type":"skProc","line":157,"col":0,"code":"proc rope(f: BiggestFloat): Rope {.gcsafe, extern: \"nro$1BiggestFloat\",\n                                   raises: [], tags: [], forbids: [].}","signature":{"return":"Rope","arguments":[{"name":"f","type":"BiggestFloat"}],"pragmas":["gcsafe","extern: \"nro$1BiggestFloat\"","raises: []","tags: []","forbids: []"]},"description":"Converts a float to a rope."},{"name":"enableCache","type":"skProc","line":165,"col":0,"code":"proc enableCache() {.gcsafe, extern: \"nro$1\", raises: [], tags: [], forbids: [].}","signature":{"pragmas":["gcsafe","extern: \"nro$1\"","raises: []","tags: []","forbids: []"]},"description":"Enables the caching of leaves. This reduces the memory footprint at the cost of runtime efficiency."},{"name":"disableCache","type":"skProc","line":170,"col":0,"code":"proc disableCache() {.gcsafe, extern: \"nro$1\", raises: [], tags: [], forbids: [].}","signature":{"pragmas":["gcsafe","extern: \"nro$1\"","raises: []","tags: []","forbids: []"]},"description":"The cache is discarded and disabled. The GC will reuse its used memory."},{"name":"`&amp;`","type":"skProc","line":175,"col":0,"code":"proc `&`(a, b: Rope): Rope {.gcsafe, extern: \"nroConcRopeRope\", raises: [],\n                             tags: [], forbids: [].}","signature":{"return":"Rope","arguments":[{"name":"a","type":"Rope"},{"name":"b","type":"Rope"}],"pragmas":["gcsafe","extern: \"nroConcRopeRope\"","raises: []","tags: []","forbids: []"]},"description":"The concatenation operator for ropes."},{"name":"`&amp;`","type":"skProc","line":191,"col":0,"code":"proc `&`(a: Rope; b: string): Rope {.gcsafe, extern: \"nroConcRopeStr\",\n                                     raises: [], tags: [], forbids: [].}","signature":{"return":"Rope","arguments":[{"name":"a","type":"Rope"},{"name":"b","type":"string"}],"pragmas":["gcsafe","extern: \"nroConcRopeStr\"","raises: []","tags: []","forbids: []"]},"description":"The concatenation operator for ropes."},{"name":"`&amp;`","type":"skProc","line":199,"col":0,"code":"proc `&`(a: string; b: Rope): Rope {.gcsafe, extern: \"nroConcStrRope\",\n                                     raises: [], tags: [], forbids: [].}","signature":{"return":"Rope","arguments":[{"name":"a","type":"string"},{"name":"b","type":"Rope"}],"pragmas":["gcsafe","extern: \"nroConcStrRope\"","raises: []","tags: []","forbids: []"]},"description":"The concatenation operator for ropes."},{"name":"`&amp;`","type":"skProc","line":207,"col":0,"code":"proc `&`(a: openArray[Rope]): Rope {.gcsafe, extern: \"nroConcOpenArray\",\n                                     raises: [], tags: [], forbids: [].}","signature":{"return":"Rope","arguments":[{"name":"a","type":"openArray[Rope]"}],"pragmas":["gcsafe","extern: \"nroConcOpenArray\"","raises: []","tags: []","forbids: []"]},"description":"The concatenation operator for an <tt class=\"docutils literal\"><span class=\"pre\"><span class=\"Identifier\">openArray</span></span></tt> of ropes."},{"name":"add","type":"skProc","line":215,"col":0,"code":"proc add(a: var Rope; b: Rope) {.gcsafe, extern: \"nro$1Rope\", raises: [],\n                                 tags: [], forbids: [].}","signature":{"arguments":[{"name":"a","type":"var Rope"},{"name":"b","type":"Rope"}],"pragmas":["gcsafe","extern: \"nro$1Rope\"","raises: []","tags: []","forbids: []"]},"description":"Adds <tt class=\"docutils literal\"><span class=\"pre\"><span class=\"Identifier\">b</span></span></tt> to the rope <tt class=\"docutils literal\"><span class=\"pre\"><span class=\"Identifier\">a</span></span></tt>."},{"name":"add","type":"skProc","line":224,"col":0,"code":"proc add(a: var Rope; b: string) {.gcsafe, extern: \"nro$1Str\", raises: [],\n                                   tags: [], forbids: [].}","signature":{"arguments":[{"name":"a","type":"var Rope"},{"name":"b","type":"string"}],"pragmas":["gcsafe","extern: \"nro$1Str\"","raises: []","tags: []","forbids: []"]},"description":"Adds <tt class=\"docutils literal\"><span class=\"pre\"><span class=\"Identifier\">b</span></span></tt> to the rope <tt class=\"docutils literal\"><span class=\"pre\"><span class=\"Identifier\">a</span></span></tt>."},{"name":"`[]`","type":"skProc","line":233,"col":0,"code":"proc `[]`(r: Rope; i: int): char {.gcsafe, extern: \"nroCharAt\", raises: [],\n                                   tags: [], forbids: [].}","signature":{"return":"char","arguments":[{"name":"r","type":"Rope"},{"name":"i","type":"int"}],"pragmas":["gcsafe","extern: \"nroCharAt\"","raises: []","tags: []","forbids: []"]},"description":"Returns the character at position <tt class=\"docutils literal\"><span class=\"pre\"><span class=\"Identifier\">i</span></span></tt> in the rope <tt class=\"docutils literal\"><span class=\"pre\"><span class=\"Identifier\">r</span></span></tt>. This is quite expensive! Worst-case: O(n). If <tt class=\"docutils literal\"><span class=\"pre\"><span class=\"Identifier\">i</span> <span class=\"Operator\">&gt;=</span> <span class=\"Identifier\">r</span><span class=\"Operator\">.</span><span class=\"Identifier\">len</span> <span class=\"Keyword\">or</span> <span class=\"Identifier\">i</span> <span class=\"Operator\">&lt;</span> <span class=\"DecNumber\">0</span></span></tt>, <tt class=\"docutils literal\"><span class=\"pre\"><span class=\"Operator\">\\</span><span class=\"DecNumber\">0</span></span></tt> is returned."},{"name":"leaves","type":"skIterator","line":257,"col":0,"code":"iterator leaves(r: Rope): string {.raises: [], tags: [], forbids: [].}","signature":{"return":"string","arguments":[{"name":"r","type":"Rope"}],"pragmas":["raises: []","tags: []","forbids: []"]},"description":"Iterates over any leaf string in the rope <tt class=\"docutils literal\"><span class=\"pre\"><span class=\"Identifier\">r</span></span></tt>."},{"name":"items","type":"skIterator","line":278,"col":0,"code":"iterator items(r: Rope): char {.raises: [], tags: [], forbids: [].}","signature":{"return":"char","arguments":[{"name":"r","type":"Rope"}],"pragmas":["raises: []","tags: []","forbids: []"]},"description":"Iterates over any character in the rope <tt class=\"docutils literal\"><span class=\"pre\"><span class=\"Identifier\">r</span></span></tt>."},{"name":"write","type":"skProc","line":283,"col":0,"code":"proc write(f: File; r: Rope) {.gcsafe, extern: \"nro$1\", raises: [IOError],\n                               tags: [WriteIOEffect], forbids: [].}","signature":{"arguments":[{"name":"f","type":"File"},{"name":"r","type":"Rope"}],"pragmas":["gcsafe","extern: \"nro$1\"","raises: [IOError]","tags: [WriteIOEffect]","forbids: []"]},"description":"Writes a rope to a file."},{"name":"write","type":"skProc","line":287,"col":0,"code":"proc write(s: Stream; r: Rope) {.gcsafe, extern: \"nroWriteStream\",\n                                 raises: [IOError, OSError],\n                                 tags: [WriteIOEffect], forbids: [].}","signature":{"arguments":[{"name":"s","type":"Stream"},{"name":"r","type":"Rope"}],"pragmas":["gcsafe","extern: \"nroWriteStream\"","raises: [IOError, OSError]","tags: [WriteIOEffect]","forbids: []"]},"description":"Writes a rope to a stream."},{"name":"`$`","type":"skProc","line":291,"col":0,"code":"proc `$`(r: Rope): string {.gcsafe, extern: \"nroToString\", raises: [], tags: [],\n                            forbids: [].}","signature":{"return":"string","arguments":[{"name":"r","type":"Rope"}],"pragmas":["gcsafe","extern: \"nroToString\"","raises: []","tags: []","forbids: []"]},"description":"Converts a rope back to a string."},{"name":"`%`","type":"skProc","line":296,"col":0,"code":"proc `%`(frmt: string; args: openArray[Rope]): Rope {.gcsafe,\n    extern: \"nroFormat\", raises: [ValueError], tags: [], forbids: [].}","signature":{"return":"Rope","arguments":[{"name":"frmt","type":"string"},{"name":"args","type":"openArray[Rope]"}],"pragmas":["gcsafe","extern: \"nroFormat\"","raises: [ValueError]","tags: []","forbids: []"]},"description":"<tt class=\"docutils literal\"><span class=\"pre\"><span class=\"Operator\">%</span></span></tt> substitution operator for ropes. Does not support the <tt class=\"docutils literal\"><span class=\"pre\"><span class=\"Operator\">$</span><span class=\"Identifier\">identifier</span></span></tt> nor <tt class=\"docutils literal\"><span class=\"pre\"><span class=\"Operator\">$</span><span class=\"Punctuation\">{</span><span class=\"Identifier\">identifier</span><span class=\"Punctuation\">}</span></span></tt> notations."},{"name":"addf","type":"skProc","line":349,"col":0,"code":"proc addf(c: var Rope; frmt: string; args: openArray[Rope]) {.gcsafe,\n    extern: \"nro$1\", raises: [ValueError], tags: [], forbids: [].}","signature":{"arguments":[{"name":"c","type":"var Rope"},{"name":"frmt","type":"string"},{"name":"args","type":"openArray[Rope]"}],"pragmas":["gcsafe","extern: \"nro$1\"","raises: [ValueError]","tags: []","forbids: []"]},"description":"Shortcut for <tt class=\"docutils literal\"><span class=\"pre\"><span class=\"Identifier\">add</span><span class=\"Punctuation\">(</span><span class=\"Identifier\">c</span><span class=\"Punctuation\">,</span> <span class=\"Identifier\">frmt</span> <span class=\"Operator\">%</span> <span class=\"Identifier\">args</span><span class=\"Punctuation\">)</span></span></tt>."},{"name":"equalsFile","type":"skProc","line":362,"col":2,"code":"proc equalsFile(r: Rope; f: File): bool {.gcsafe, extern: \"nro$1File\",\n    raises: [IOError], tags: [ReadIOEffect], forbids: [].}","signature":{"return":"bool","arguments":[{"name":"r","type":"Rope"},{"name":"f","type":"File"}],"pragmas":["gcsafe","extern: \"nro$1File\"","raises: [IOError]","tags: [ReadIOEffect]","forbids: []"]},"description":"Returns true if the contents of the file <tt class=\"docutils literal\"><span class=\"pre\"><span class=\"Identifier\">f</span></span></tt> equal <tt class=\"docutils literal\"><span class=\"pre\"><span class=\"Identifier\">r</span></span></tt>."},{"name":"equalsFile","type":"skProc","line":389,"col":2,"code":"proc equalsFile(r: Rope; filename: string): bool {.gcsafe, extern: \"nro$1Str\",\n    raises: [IOError], tags: [ReadIOEffect], forbids: [].}","signature":{"return":"bool","arguments":[{"name":"r","type":"Rope"},{"name":"filename","type":"string"}],"pragmas":["gcsafe","extern: \"nro$1Str\"","raises: [IOError]","tags: [ReadIOEffect]","forbids: []"]},"description":"Returns true if the contents of the file <tt class=\"docutils literal\"><span class=\"pre\"><span class=\"Identifier\">f</span></span></tt> equal <tt class=\"docutils literal\"><span class=\"pre\"><span class=\"Identifier\">r</span></span></tt>. If <tt class=\"docutils literal\"><span class=\"pre\"><span class=\"Identifier\">f</span></span></tt> does not exist, false is returned."}]}