{"orig":"/Users/kalaverin/src/lang/nim/lib/std/jsfetch.nim","nimble":"stdlib","moduleDescription":"<ul class=\"simple\"><li>Fetch for the JavaScript target: <a class=\"reference external\" href=\"https://developer.mozilla.org/docs/Web/API/Fetch_API\">https://developer.mozilla.org/docs/Web/API/Fetch_API</a></li>\n</ul>\n","entries":[{"name":"FetchOptions","type":"skType","line":11,"col":16,"code":"FetchOptions = ref object of JsRoot\n  keepalive*: bool\n  metod* {.importjs: \"method\".}: cstring\n  body*, integrity*, referrer*, mode*, credentials*, cache*, redirect*,\n  referrerPolicy*: cstring\n  headers*: Headers","description":"Options for Fetch API."},{"name":"FetchModes","type":"skType","line":17,"col":14,"code":"FetchModes = enum\n  fmCors = \"cors\", fmNoCors = \"no-cors\", fmSameOrigin = \"same-origin\"","description":"Mode options."},{"name":"FetchCredentials","type":"skType","line":22,"col":20,"code":"FetchCredentials = enum\n  fcInclude = \"include\", fcSameOrigin = \"same-origin\", fcOmit = \"omit\"","description":"Credential options. See <a class=\"reference external\" href=\"https://developer.mozilla.org/en-US/docs/Web/API/Request/credentials\">https://developer.mozilla.org/en-US/docs/Web/API/Request/credentials</a>"},{"name":"FetchCaches","type":"skType","line":27,"col":15,"code":"FetchCaches = enum\n  fchDefault = \"default\", fchNoStore = \"no-store\", fchReload = \"reload\",\n  fchNoCache = \"no-cache\", fchForceCache = \"force-cache\"","description":"<a class=\"reference external\" href=\"https://developer.mozilla.org/docs/Web/API/Request/cache\">https://developer.mozilla.org/docs/Web/API/Request/cache</a>"},{"name":"FetchRedirects","type":"skType","line":34,"col":18,"code":"FetchRedirects = enum\n  frFollow = \"follow\", frError = \"error\", frManual = \"manual\"","description":"Redirects options."},{"name":"FetchReferrerPolicies","type":"skType","line":39,"col":25,"code":"FetchReferrerPolicies = enum\n  frpNoReferrer = \"no-referrer\",\n  frpNoReferrerWhenDowngrade = \"no-referrer-when-downgrade\",\n  frpOrigin = \"origin\", frpOriginWhenCrossOrigin = \"origin-when-cross-origin\",\n  frpUnsafeUrl = \"unsafe-url\"","description":"Referrer Policy options."},{"name":"Response","type":"skType","line":46,"col":12,"code":"Response = ref object of JsRoot\n  bodyUsed*, ok*, redirected*: bool\n  typ* {.importjs: \"type\".}: cstring\n  url*, statusText*: cstring\n  status*: cint\n  headers*: Headers\n  body*: cstring","description":"<a class=\"reference external\" href=\"https://developer.mozilla.org/en-US/docs/Web/API/Response\">https://developer.mozilla.org/en-US/docs/Web/API/Response</a>"},{"name":"Request","type":"skType","line":54,"col":11,"code":"Request = ref object of JsRoot\n  bodyUsed*, ok*, redirected*: bool\n  typ* {.importjs: \"type\".}: cstring\n  url*, statusText*: cstring\n  status*: cint\n  headers*: Headers\n  body*: cstring","description":"<a class=\"reference external\" href=\"https://developer.mozilla.org/en-US/docs/Web/API/Request\">https://developer.mozilla.org/en-US/docs/Web/API/Request</a>"},{"name":"newResponse","type":"skProc","line":62,"col":0,"code":"func newResponse(body: cstring | FormData): Response {.\n    importjs: \"(new Response(#))\", raises: [], tags: [], forbids: [].}","signature":{"return":"Response","arguments":[{"name":"body","type":"cstring | FormData"}],"pragmas":["importjs: \"(new Response(#))\"","raises: []","tags: []","forbids: []"],"genericParams":[{"name":"body:type","types":"FormData"}]},"description":"Constructor for <tt class=\"docutils literal\"><span class=\"pre\"><span class=\"Identifier\">Response</span></span></tt>. This does <em>not</em> call <tt class=\"docutils literal\"><span class=\"pre\"><span class=\"Identifier\">fetch</span><span class=\"Punctuation\">(</span><span class=\"Punctuation\">)</span></span></tt>. Same as <tt class=\"docutils literal\"><span class=\"pre\"><span class=\"Identifier\">new</span> <span class=\"Identifier\">Response</span><span class=\"Punctuation\">(</span><span class=\"Punctuation\">)</span></span></tt>."},{"name":"newRequest","type":"skProc","line":65,"col":0,"code":"func newRequest(url: cstring): Request {.importjs: \"(new Request(#))\",\n    raises: [], tags: [], forbids: [].}","signature":{"return":"Request","arguments":[{"name":"url","type":"cstring"}],"pragmas":["importjs: \"(new Request(#))\"","raises: []","tags: []","forbids: []"]},"description":"Constructor for <tt class=\"docutils literal\"><span class=\"pre\"><span class=\"Identifier\">Request</span></span></tt>. This does <em>not</em> call <tt class=\"docutils literal\"><span class=\"pre\"><span class=\"Identifier\">fetch</span><span class=\"Punctuation\">(</span><span class=\"Punctuation\">)</span></span></tt>. Same as <tt class=\"docutils literal\"><span class=\"pre\"><span class=\"Identifier\">new</span> <span class=\"Identifier\">Request</span><span class=\"Punctuation\">(</span><span class=\"Punctuation\">)</span></span></tt>."},{"name":"newRequest","type":"skProc","line":68,"col":0,"code":"func newRequest(url: cstring; fetchOptions: FetchOptions): Request {.\n    importjs: \"(new Request(#, #))\", raises: [], tags: [], forbids: [].}","signature":{"return":"Request","arguments":[{"name":"url","type":"cstring"},{"name":"fetchOptions","type":"FetchOptions"}],"pragmas":["importjs: \"(new Request(#, #))\"","raises: []","tags: []","forbids: []"]},"description":"Constructor for <tt class=\"docutils literal\"><span class=\"pre\"><span class=\"Identifier\">Request</span></span></tt> with <tt class=\"docutils literal\"><span class=\"pre\"><span class=\"Identifier\">fetchOptions</span></span></tt>. Same as <tt class=\"docutils literal\"><span class=\"pre\"><span class=\"Identifier\">fetch</span><span class=\"Punctuation\">(</span><span class=\"Identifier\">url</span><span class=\"Punctuation\">,</span> <span class=\"Identifier\">fetchOptions</span><span class=\"Punctuation\">)</span></span></tt>."},{"name":"clone","type":"skProc","line":71,"col":0,"code":"func clone(self: Response | Request): Response {.importjs: \"#.$1()\", raises: [],\n    tags: [], forbids: [].}","signature":{"return":"Response","arguments":[{"name":"self","type":"Response | Request"}],"pragmas":["importjs: \"#.$1()\"","raises: []","tags: []","forbids: []"],"genericParams":[{"name":"self:type","types":"Request"}]},"description":"<a class=\"reference external\" href=\"https://developer.mozilla.org/en-US/docs/Web/API/Response/clone\">https://developer.mozilla.org/en-US/docs/Web/API/Response/clone</a>"},{"name":"text","type":"skProc","line":74,"col":0,"code":"proc text(self: Response): Future[cstring] {.importjs: \"#.$1()\", raises: [],\n    tags: [], forbids: [].}","signature":{"return":"Future[cstring]","arguments":[{"name":"self","type":"Response"}],"pragmas":["importjs: \"#.$1()\"","raises: []","tags: []","forbids: []"]},"description":"<a class=\"reference external\" href=\"https://developer.mozilla.org/en-US/docs/Web/API/Response/text\">https://developer.mozilla.org/en-US/docs/Web/API/Response/text</a>"},{"name":"json","type":"skProc","line":77,"col":0,"code":"proc json(self: Response): Future[JsObject] {.importjs: \"#.$1()\", raises: [],\n    tags: [], forbids: [].}","signature":{"return":"Future[JsObject]","arguments":[{"name":"self","type":"Response"}],"pragmas":["importjs: \"#.$1()\"","raises: []","tags: []","forbids: []"]},"description":"<a class=\"reference external\" href=\"https://developer.mozilla.org/en-US/docs/Web/API/Response/json\">https://developer.mozilla.org/en-US/docs/Web/API/Response/json</a>"},{"name":"formData","type":"skProc","line":80,"col":0,"code":"proc formData(self: Response): Future[FormData] {.importjs: \"#.$1()\",\n    raises: [], tags: [], forbids: [].}","signature":{"return":"Future[FormData]","arguments":[{"name":"self","type":"Response"}],"pragmas":["importjs: \"#.$1()\"","raises: []","tags: []","forbids: []"]},"description":"<a class=\"reference external\" href=\"https://developer.mozilla.org/en-US/docs/Web/API/Response/formData\">https://developer.mozilla.org/en-US/docs/Web/API/Response/formData</a>"},{"name":"unsafeNewFetchOptions","type":"skProc","line":83,"col":0,"code":"proc unsafeNewFetchOptions(metod, body, mode, credentials, cache, referrerPolicy: cstring;\n                           keepalive: bool; redirect = \"follow\".cstring;\n                           referrer = \"client\".cstring; integrity = \"\".cstring;\n                           headers: Headers = newHeaders()): FetchOptions {.importjs: \"{method: #, body: #, mode: #, credentials: #, cache: #, referrerPolicy: #, keepalive: #, redirect: #, referrer: #, integrity: #, headers: #}\",\n    raises: [], tags: [], forbids: [].}","signature":{"return":"FetchOptions","arguments":[{"name":"metod","type":"cstring"},{"name":"body","type":"cstring"},{"name":"mode","type":"cstring"},{"name":"credentials","type":"cstring"},{"name":"cache","type":"cstring"},{"name":"referrerPolicy","type":"cstring"},{"name":"keepalive","type":"bool"},{"name":"redirect","type":"","default":"\"follow\".cstring"},{"name":"referrer","type":"","default":"\"client\".cstring"},{"name":"integrity","type":"","default":"\"\".cstring"},{"name":"headers","type":"Headers","default":"newHeaders()"}],"pragmas":["importjs: \"{method: #, body: #, mode: #, credentials: #, cache: #, referrerPolicy: #, keepalive: #, redirect: #, referrer: #, integrity: #, headers: #}\"","raises: []","tags: []","forbids: []"]},"description":"<div class=\"admonition admonition-warning\"><span class=\"admonition-warning-text\"><b>Warning:</b></span>\nUnsafe <tt class=\"docutils literal\"><span class=\"pre\"><span class=\"Identifier\">newfetchOptions</span></span></tt>.</div>\n"},{"name":"newfetchOptions","type":"skProc","line":88,"col":0,"code":"func newfetchOptions(metod = HttpGet; body: cstring = nil; mode = fmCors;\n                     credentials = fcSameOrigin; cache = fchDefault;\n                     referrerPolicy = frpNoReferrerWhenDowngrade;\n                     keepalive = false; redirect = frFollow;\n                     referrer = \"client\".cstring; integrity = \"\".cstring;\n                     headers: Headers = newHeaders()): FetchOptions {.\n    raises: [], tags: [], forbids: [].}","signature":{"return":"FetchOptions","arguments":[{"name":"metod","type":"","default":"HttpGet"},{"name":"body","type":"cstring","default":"nil"},{"name":"mode","type":"","default":"fmCors"},{"name":"credentials","type":"","default":"fcSameOrigin"},{"name":"cache","type":"","default":"fchDefault"},{"name":"referrerPolicy","type":"","default":"frpNoReferrerWhenDowngrade"},{"name":"keepalive","type":"","default":"false"},{"name":"redirect","type":"","default":"frFollow"},{"name":"referrer","type":"","default":"\"client\".cstring"},{"name":"integrity","type":"","default":"\"\".cstring"},{"name":"headers","type":"Headers","default":"newHeaders()"}],"pragmas":["raises: []","tags: []","forbids: []"]},"description":"Constructor for <tt class=\"docutils literal\"><span class=\"pre\"><span class=\"Identifier\">FetchOptions</span></span></tt>."},{"name":"fetch","type":"skProc","line":108,"col":0,"code":"proc fetch(url: cstring | Request): Future[Response] {.importjs: \"$1(#)\",\n    raises: [], tags: [], forbids: [].}","signature":{"return":"Future[Response]","arguments":[{"name":"url","type":"cstring | Request"}],"pragmas":["importjs: \"$1(#)\"","raises: []","tags: []","forbids: []"],"genericParams":[{"name":"url:type","types":"Request"}]},"description":"<tt class=\"docutils literal\"><span class=\"pre\"><span class=\"Identifier\">fetch</span><span class=\"Punctuation\">(</span><span class=\"Punctuation\">)</span></span></tt> API, simple <tt class=\"docutils literal\"><span class=\"pre\"><span class=\"Identifier\">GET</span></span></tt> only, returns a <tt class=\"docutils literal\"><span class=\"pre\"><span class=\"Identifier\">Future</span><span class=\"Punctuation\">[</span><span class=\"Identifier\">Response</span><span class=\"Punctuation\">]</span></span></tt>."},{"name":"fetch","type":"skProc","line":111,"col":0,"code":"proc fetch(url: cstring | Request; options: FetchOptions): Future[Response] {.\n    importjs: \"$1(#, #)\", raises: [], tags: [], forbids: [].}","signature":{"return":"Future[Response]","arguments":[{"name":"url","type":"cstring | Request"},{"name":"options","type":"FetchOptions"}],"pragmas":["importjs: \"$1(#, #)\"","raises: []","tags: []","forbids: []"],"genericParams":[{"name":"url:type","types":"Request"}]},"description":"<tt class=\"docutils literal\"><span class=\"pre\"><span class=\"Identifier\">fetch</span><span class=\"Punctuation\">(</span><span class=\"Punctuation\">)</span></span></tt> API that takes a <tt class=\"docutils literal\"><span class=\"pre\"><span class=\"Identifier\">FetchOptions</span></span></tt>, returns a <tt class=\"docutils literal\"><span class=\"pre\"><span class=\"Identifier\">Future</span><span class=\"Punctuation\">[</span><span class=\"Identifier\">Response</span><span class=\"Punctuation\">]</span></span></tt>."},{"name":"toCstring","type":"skProc","line":114,"col":0,"code":"func toCstring(self: Request | Response | FetchOptions): cstring {.\n    importjs: \"JSON.stringify(#)\", raises: [], tags: [], forbids: [].}","signature":{"return":"cstring","arguments":[{"name":"self","type":"Request | Response | FetchOptions"}],"pragmas":["importjs: \"JSON.stringify(#)\"","raises: []","tags: []","forbids: []"],"genericParams":[{"name":"self:type","types":"FetchOptions"}]}},{"name":"`$`","type":"skProc","line":116,"col":0,"code":"func `$`(self: Request | Response | FetchOptions): string","signature":{"return":"string","arguments":[{"name":"self","type":"Request | Response | FetchOptions"}],"genericParams":[{"name":"self:type","types":"FetchOptions"}]}}]}